pycti/__init__.py
pycti/api/__init__.py
pycti/api/opencti_api_client.py
pycti/api/opencti_api_connector.py
pycti/api/opencti_api_draft.py
pycti/api/opencti_api_internal_file.py
pycti/api/opencti_api_notification.py
pycti/api/opencti_api_pir.py
pycti/api/opencti_api_playbook.py
pycti/api/opencti_api_public_dashboard.py
pycti/api/opencti_api_trash.py
pycti/api/opencti_api_work.py
pycti/api/opencti_api_workspace.py
pycti/connector/__init__.py
pycti/connector/opencti_connector.py
pycti/connector/opencti_connector_helper.py
pycti/connector/opencti_metric_handler.py
pycti/entities/__init__.py
pycti/entities/opencti_attack_pattern.py
pycti/entities/opencti_campaign.py
pycti/entities/opencti_capability.py
pycti/entities/opencti_case_incident.py
pycti/entities/opencti_case_rfi.py
pycti/entities/opencti_case_rft.py
pycti/entities/opencti_channel.py
pycti/entities/opencti_course_of_action.py
pycti/entities/opencti_data_component.py
pycti/entities/opencti_data_source.py
pycti/entities/opencti_event.py
pycti/entities/opencti_external_reference.py
pycti/entities/opencti_feedback.py
pycti/entities/opencti_group.py
pycti/entities/opencti_grouping.py
pycti/entities/opencti_identity.py
pycti/entities/opencti_incident.py
pycti/entities/opencti_indicator.py
pycti/entities/opencti_infrastructure.py
pycti/entities/opencti_intrusion_set.py
pycti/entities/opencti_kill_chain_phase.py
pycti/entities/opencti_label.py
pycti/entities/opencti_language.py
pycti/entities/opencti_location.py
pycti/entities/opencti_malware.py
pycti/entities/opencti_malware_analysis.py
pycti/entities/opencti_marking_definition.py
pycti/entities/opencti_narrative.py
pycti/entities/opencti_note.py
pycti/entities/opencti_observed_data.py
pycti/entities/opencti_opinion.py
pycti/entities/opencti_report.py
pycti/entities/opencti_role.py
pycti/entities/opencti_security_coverage.py
pycti/entities/opencti_settings.py
pycti/entities/opencti_stix.py
pycti/entities/opencti_stix_core_object.py
pycti-6.9.13.dist-info/METADATA
pycti-6.9.13.dist-info/WHEEL
pycti-6.9.13.dist-info/top_level.txt
pycti-6.9.13.dist-info/RECORD
