Metadata-Version: 2.4
Name: pycti
Version: 6.9.13
Summary: Python API client for OpenCTI.
Home-page: https://github.com/OpenCTI-Platform/opencti/client-python
Author: Filigran
Author-email: contact@filigran.io
Maintainer: Filigran
License: Apache
Classifier: Development Status :: 5 - Production/Stable
Classifier: Intended Audience :: Developers
Classifier: Intended Audience :: Information Technology
Classifier: Intended Audience :: Science/Research
Classifier: License :: OSI Approved :: Apache Software License
Classifier: Natural Language :: English
Classifier: Natural Language :: French
Classifier: Operating System :: OS Independent
Classifier: Programming Language :: Python :: 3
Classifier: Topic :: Security
Classifier: Topic :: Software Development :: Libraries :: Python Modules
Requires-Python: >=3.7
Requires-Dist: boto3~=1.38.27
Requires-Dist: datefinder~=0.7.3
Requires-Dist: pika~=1.3.0
Requires-Dist: pydantic<3,>=2.8.2
Requires-Dist: python-magic~=0.4.27; sys_platform == "linux" or sys_platform == "darwin"
Requires-Dist: python-magic-bin~=0.4.14; sys_platform == "win32"
Requires-Dist: python_json_logger~=3.3.0
Requires-Dist: PyYAML~=6.0
Requires-Dist: requests<3,>=2.32.0
Requires-Dist: setuptools~=80.9.0
Requires-Dist: cachetools~=5.5.2
Requires-Dist: prometheus-client~=0.22.1
Requires-Dist: opentelemetry-api~=1.35.0
Requires-Dist: opentelemetry-sdk~=1.35.0
Requires-Dist: deprecation~=2.1.0
Requires-Dist: fastapi<0.125.0,>=0.124.0
Requires-Dist: uvicorn[standard]<0.36.0,>=0.34.0
Requires-Dist: filigran-sseclient>=1.0.2
Requires-Dist: stix2~=3.0.1
Provides-Extra: dev
Requires-Dist: black~=25.11.0; extra == "dev"
Requires-Dist: build~=1.4.0; extra == "dev"
Requires-Dist: isort~=6.0.0; extra == "dev"
Requires-Dist: types-pytz~=2025.2.0.20250326; extra == "dev"
Requires-Dist: pre-commit~=4.5.0; extra == "dev"
Requires-Dist: pytest-cases~=3.9.1; extra == "dev"
Requires-Dist: pytest-cov~=7.0.0; extra == "dev"
Requires-Dist: pytest_randomly~=4.0.1; extra == "dev"
Requires-Dist: pytest~=8.4.1; extra == "dev"
Requires-Dist: types-python-dateutil~=2.9.0; extra == "dev"
Requires-Dist: wheel~=0.45.1; extra == "dev"
Provides-Extra: doc
Requires-Dist: sphinx-autoapi>=3.0.0; extra == "doc"
Requires-Dist: sphinx<9,>=8.2; extra == "doc"
Requires-Dist: sphinx-autodoc-typehints>=3.0.0; extra == "doc"
Requires-Dist: sphinx-rtd-theme>=3.0.0; extra == "doc"
